aieng/topic/impl/__init__.py
aieng/topic/impl/example_impl.py
tests/aieng/topic/impl/test_example_impl.py
aieng_topic_impl-0.1.0.dist-info/METADATA
aieng_topic_impl-0.1.0.dist-info/WHEEL
aieng_topic_impl-0.1.0.dist-info/RECORD
